cryptobyte/__about__.py
cryptobyte/__init__.py
cryptobyte/ai/a_star.py
cryptobyte/ai/association.py
cryptobyte/ai/bfs_dfs.py
cryptobyte/ai/decisiontree.py
cryptobyte/ai/email_spam.py
cryptobyte/ai/knn.py
cryptobyte/ai/naive.py
cryptobyte/ai/svm.py
cryptobyte/ins/ceaser.py
cryptobyte/ins/hellman.py
cryptobyte/ins/md5.py
cryptobyte/ins/railfence.py
cryptobyte/ins/rsa.py
cryptobyte/ins/sha.py
cryptobyte-0.2.0.dist-info/METADATA
cryptobyte-0.2.0.dist-info/WHEEL
cryptobyte-0.2.0.dist-info/licenses/LICENSE.txt
cryptobyte-0.2.0.dist-info/RECORD
