Metadata-Version: 2.3
Name: cryptobyte
Version: 0.2.0
Project-URL: Documentation, https://github.com/Zaeem20/cryptobyte#readme
Project-URL: Issues, https://github.com/Zaeem20/cryptobyte/issues
Project-URL: Source, https://github.com/Zaeem20/cryptobyte
Author-email: Johnny dev <devjohnny123@gmail.com>
License-Expression: MIT
License-File: LICENSE.txt
Classifier: Development Status :: 4 - Beta
Classifier: Programming Language :: Python
Classifier: Programming Language :: Python :: 3.8
Classifier: Programming Language :: Python :: 3.9
Classifier: Programming Language :: Python :: 3.10
Classifier: Programming Language :: Python :: 3.11
Classifier: Programming Language :: Python :: 3.12
Classifier: Programming Language :: Python :: Implementation :: CPython
Classifier: Programming Language :: Python :: Implementation :: PyPy
Requires-Python: >=3.8
Requires-Dist: matplotlib
Requires-Dist: mlxtend
Requires-Dist: numpy
Requires-Dist: pandas
Requires-Dist: pycryptodome
Requires-Dist: scikit-learn
Requires-Dist: tensorflow
